flashcontainer/__init__.py
flashcontainer/__main__.py
flashcontainer/a2lwriter.py
flashcontainer/byteconv.py
flashcontainer/cfilewriter.py
flashcontainer/checksum.py
flashcontainer/datamodel.py
flashcontainer/fileargparse.py
flashcontainer/gnuldwriter.py
flashcontainer/hexwriter.py
flashcontainer/packageinfo.py
flashcontainer/pargen.py
flashcontainer/pargen_1.0.xsd
flashcontainer/pyhexdumpwriter.py
flashcontainer/tc3xx.py
flashcontainer/tc3xx_abmhd.py
flashcontainer/tc3xx_cmd.py
flashcontainer/xmlparser.py
flashcontainer-0.5.0.dist-info/LICENSE
flashcontainer-0.5.0.dist-info/METADATA
flashcontainer-0.5.0.dist-info/WHEEL
flashcontainer-0.5.0.dist-info/entry_points.txt
flashcontainer-0.5.0.dist-info/top_level.txt
flashcontainer-0.5.0.dist-info/RECORD
