Metadata-Version: 2.1
Name: flashcontainer
Version: 0.5.0
Summary: A tooling for flashable parameter data container generation
Author: Haju Schulz
Author-email: Haju Schulz <haju.schulz@online.de>
License: BSD License
Project-URL: repository, https://github.com/nhjschulz/flashcontainer
Classifier: Development Status :: 4 - Beta
Classifier: Intended Audience :: Developers
Classifier: Topic :: Software Development :: Build Tools
Classifier: License :: OSI Approved :: BSD License
Classifier: Programming Language :: Python :: 3.8
Classifier: Programming Language :: Python :: 3.9
Classifier: Programming Language :: Python :: 3.10
Classifier: Programming Language :: Python :: 3.11
Requires-Python: >=3.8
License-File: LICENSE
Requires-Dist: crc (>=3.0)
Requires-Dist: intelhex (>=2.3.0)
Requires-Dist: json5 (>=0.9.10)
Requires-Dist: lxml (>=4.9.2)
Requires-Dist: toml (>=0.10.2)
Provides-Extra: test
Requires-Dist: pytest (>5.0.0) ; extra == 'test'
Requires-Dist: pytest-cov[all] ; extra == 'test'
